openmdao_extensions/__init__.py
openmdao_extensions/egobox_doe_driver.py
openmdao_extensions/egobox_egor_driver.py
openmdao_extensions/onera_sego_driver.py
openmdao_extensions/openturns_doe_driver.py
openmdao_extensions/reckless_nonlinear_block_gs.py
openmdao_extensions/salib_doe_driver.py
openmdao_extensions/smt_doe_driver.py
openmdao_extensions-1.3.0.dist-info/LICENSE
openmdao_extensions-1.3.0.dist-info/METADATA
openmdao_extensions-1.3.0.dist-info/WHEEL
openmdao_extensions-1.3.0.dist-info/entry_points.txt
openmdao_extensions-1.3.0.dist-info/top_level.txt
openmdao_extensions-1.3.0.dist-info/zip-safe
openmdao_extensions-1.3.0.dist-info/RECORD
