Metadata-Version: 2.1
Name: openmdao-extensions
Version: 1.3.0
Summary: Additional solvers and drivers for OpenMDAO framework
Home-page: https://github.com/OneraHub/openmdao_extensions
Download-URL: https://github.com/OneraHub/openmdao_extensions/releases
Author: Rémi Lafage
Author-email: remi.lafage@onera.fr
License: Apache License, Version 2.0
Keywords: openmdao openmdao_driver openmdao_nl_solver
Classifier: Development Status :: 5 - Production/Stable
Classifier: Intended Audience :: Science/Research
Classifier: Intended Audience :: Developers
Classifier: License :: OSI Approved :: Apache Software License
Classifier: Programming Language :: Python
Classifier: Programming Language :: Python :: 3
Classifier: Topic :: Software Development
Classifier: Topic :: Scientific/Engineering
Classifier: Operating System :: Microsoft :: Windows
Classifier: Operating System :: Unix
Classifier: Operating System :: MacOS
Requires-Python: >=3.8
License-File: LICENSE
Requires-Dist: openmdao >=3.0.0
Provides-Extra: egobox
Requires-Dist: egobox ~=0.14.0 ; extra == 'egobox'
